[
  {
    "date": "2026-07-15",
    "imp7": 18,
    "clicks7": 1,
    "pos7": 48.833333333333336,
    "impPrior7": 14,
    "earningPages7": 4,
    "indexedCount": 15,
    "headTerms": {
      "best twink sites": {
        "imp": 1,
        "pos": 29
      },
      "twink sites": null,
      "best gay twink sites": {
        "imp": 3,
        "pos": 34.3
      },
      "twink websites": null
    },
    "verdict": "FLAT"
  },
  {
    "date": "2026-07-16",
    "imp7": 18,
    "clicks7": 1,
    "pos7": 45.05555555555556,
    "impPrior7": 16,
    "earningPages7": 5,
    "indexedCount": 15,
    "headTerms": {
      "best twink sites": null,
      "twink sites": null,
      "best gay twink sites": {
        "imp": 3,
        "pos": 34.3
      },
      "twink websites": null
    },
    "verdict": "FLAT"
  }
]
